{
  "noise_floor": 0.001,
  "tracking_thresh": 0.015,
  "sustain_thresh": 0.05,
  "transient_delta": 0.08,
  "duck_burst_level": 0.15,
  "duck_attack_coef": 0.7,
  "duck_release_coef": 0.04,
  "burst_duration_ticks": 60,
  "burst_immediate_count": 2,
  "density_burst": 25.0,
  "density_sustain": 10.0,
  "density_decay": 4.0,
  "attack_region_min_offset_samples": 4410,
  "attack_region_max_offset_samples": 5512,
  "body_region_min_offset_samples": 17640,
  "body_region_max_offset_samples": 22050,
  "memory_region_min_offset_samples": 35280,
  "memory_region_max_offset_samples": 44100,
  "micro_duration_ms_min": 8.0,
  "micro_duration_ms_max": 16.0,
  "short_duration_ms_min": 25.0,
  "short_duration_ms_max": 50.0,
  "body_duration_ms_min": 80.0,
  "body_duration_ms_max": 250.0,
  "rng_seed": 1,
  "mix_dry_gain": 1.0,
  "mix_wet_gain": 0.8
}
